{
  "collectedAt": "2026-03-24T15:17:51.589Z",
  "cards": {
    "totalRepos": 2490,
    "activityRate": "0.48",
    "staleRate": "0.27",
    "totalDownloads": {
      "total": 315165438,
      "packages": [
        {
          "package": "ajv",
          "downloads": 280106752
        },
        {
          "package": "json-schema",
          "downloads": 35058686
        }
      ]
    }
  },
  "charts": {
    "growth": {
      "labels": [
        "2026-03-23T23:03:25.814Z",
        "2026-03-24T15:17:51.581Z"
      ],
      "data": [
        null,
        null
      ]
    },
    "activity": {
      "labels": [
        "2026-03-23T23:03:25.814Z",
        "2026-03-24T15:17:51.581Z"
      ],
      "data": [
        "0.47",
        "0.48"
      ]
    },
    "activeRepos": {
      "labels": [
        "2026-03-23T23:03:25.814Z",
        "2026-03-24T15:17:51.581Z"
      ],
      "data": [
        null,
        null
      ]
    }
  },
  "health": {
    "status": "moderate",
    "label": "Moderate"
  },
  "trend": "up",
  "activityDistribution": {
    "active": 48,
    "inactive": 25,
    "stale": 27
  }
}